smartystreets_python_sdk/__init__.py
smartystreets_python_sdk/batch.py
smartystreets_python_sdk/client_builder.py
smartystreets_python_sdk/custom_header_sender.py
smartystreets_python_sdk/errors.py
smartystreets_python_sdk/exceptions.py
smartystreets_python_sdk/license_sender.py
smartystreets_python_sdk/native_serializer.py
smartystreets_python_sdk/proxy.py
smartystreets_python_sdk/request.py
smartystreets_python_sdk/requests_sender.py
smartystreets_python_sdk/response.py
smartystreets_python_sdk/retry_sender.py
smartystreets_python_sdk/shared_credentials.py
smartystreets_python_sdk/signing_sender.py
smartystreets_python_sdk/static_credentials.py
smartystreets_python_sdk/status_code_sender.py
smartystreets_python_sdk/url_prefix_sender.py
smartystreets_python_sdk/international_autocomplete/__init__.py
smartystreets_python_sdk/international_autocomplete/candidate.py
smartystreets_python_sdk/international_autocomplete/client.py
smartystreets_python_sdk/international_autocomplete/lookup.py
smartystreets_python_sdk/international_street/__init__.py
smartystreets_python_sdk/international_street/analysis.py
smartystreets_python_sdk/international_street/candidate.py
smartystreets_python_sdk/international_street/changes.py
smartystreets_python_sdk/international_street/client.py
smartystreets_python_sdk/international_street/components.py
smartystreets_python_sdk/international_street/language_mode.py
smartystreets_python_sdk/international_street/lookup.py
smartystreets_python_sdk/international_street/metadata.py
smartystreets_python_sdk/international_street/rootlevel.py
smartystreets_python_sdk/us_autocomplete/__init__.py
smartystreets_python_sdk/us_autocomplete/client.py
smartystreets_python_sdk/us_autocomplete/geolocation_type.py
smartystreets_python_sdk/us_autocomplete/lookup.py
smartystreets_python_sdk/us_autocomplete/suggestion.py
smartystreets_python_sdk/us_autocomplete_pro/__init__.py
smartystreets_python_sdk/us_autocomplete_pro/client.py
smartystreets_python_sdk-0.0.0.dist-info/LICENSE.md
smartystreets_python_sdk-0.0.0.dist-info/METADATA
smartystreets_python_sdk-0.0.0.dist-info/WHEEL
smartystreets_python_sdk-0.0.0.dist-info/top_level.txt
smartystreets_python_sdk-0.0.0.dist-info/RECORD
