Metadata-Version: 2.1
Name: smartystreets-python-sdk
Version: 0.0.0
Summary: An official library to help Python developers easily access the SmartyStreets APIs
Home-page: https://github.com/smartystreets/smartystreets-python-sdk
Download-URL: https://github.com/smartystreets/smartystreets-python-sdk/tarball/0.0.0
Author: SmartyStreets SDK Team
Author-email: support@smartystreets.com
License: Apache 2
Keywords: smartystreets,smarty,address,validation,verification,street,sdk,library,geocode
Classifier: Development Status :: 5 - Production/Stable
Classifier: Intended Audience :: Developers
Classifier: License :: OSI Approved :: Apache Software License
Classifier: Natural Language :: English
Classifier: Programming Language :: Python :: 2.7
Classifier: Programming Language :: Python :: 3
License-File: LICENSE.md
Requires-Dist: requests
